{
    "type": "minecraft:crafting_shapeless",
    "ingredients": [
        {
            "item": "minecraft:paper"
        },
        {
            "item": "minecraft:paper"
        },
        {
            "item": "minecraft:paper"
        },
        {
            "item": "minecraft:red_dye"
        },
        {
            "item": "minecraft:stick"
        },
        {
            "item": "minecraft:feather"
        }
    ],
    "result": {
        "item": "arcanemechina:predrawnrune",
        "count": 1
    }
}